chtk/__init__.py
chtk/chart.py
chtk/chtk.py
chtk/visualization.py
chtk-0.0.2.dist-info/WHEEL
chtk-0.0.2.dist-info/METADATA
chtk-0.0.2.dist-info/RECORD
